attacus/__about__.py
attacus/__init__.py
attacus/app.py
attacus/artifacts.py
attacus/assets.py
attacus/attacus.pyd
attacus/build.py
attacus/cli.py
attacus/flutter_config.py
attacus/flutter_view.py
attacus/install.py
attacus/post_build.py
attacus/project.py
attacus/pyproject.py
attacus/uninstall.py
attacus-0.1.6.dist-info/LICENSE
attacus-0.1.6.dist-info/METADATA
attacus-0.1.6.dist-info/WHEEL
attacus-0.1.6.dist-info/entry_points.txt
attacus-0.1.6.dist-info/top_level.txt
attacus-0.1.6.dist-info/RECORD
