Metadata-Version: 2.1
Name: attacus
Version: 0.1.6
Summary: Python Flutter Extension
Author-email: Kurtis Fields <kurtisfields@gmail.com>
License: MIT License        
Project-URL: homepage, https://github.com/crunge/attacus
Project-URL: documentation, https://crungelab.github.io/attacus/
Project-URL: repository, https://github.com/crungelab/attacus
Project-URL: changelog, https://github.com/crungelab/attacus/blob/main/CHANGELOG.md
Classifier: Development Status :: 4 - Beta
Classifier: Programming Language :: Python
Classifier: Programming Language :: Python :: 3.8
Classifier: Programming Language :: Python :: 3.9
Classifier: Programming Language :: Python :: 3.10
Classifier: Programming Language :: Python :: 3.11
Classifier: Programming Language :: Python :: Implementation :: CPython
Classifier: Programming Language :: Python :: Implementation :: PyPy
Requires-Python: >=3.8
License-File: LICENSE
Requires-Dist: loguru (~=0.7.0)
Requires-Dist: platformdirs (~=3.5.1)
Requires-Dist: requests (~=2.31.0)
Requires-Dist: rich (~=13.3.5)
Requires-Dist: click (~=8.1.3)
Provides-Extra: dev
Requires-Dist: black (~=22.12.0) ; extra == 'dev'
Provides-Extra: test
Requires-Dist: pytest (~=7.2.1) ; extra == 'test'
